thumbor_plugins/optimizers/gifv/__init__.py
thumbor_plugins/optimizers/gifv/config.py
thumbor_plugins_gifv-0.1.5.dist-info/METADATA
thumbor_plugins_gifv-0.1.5.dist-info/WHEEL
thumbor_plugins_gifv-0.1.5.dist-info/top_level.txt
thumbor_plugins_gifv-0.1.5.dist-info/RECORD
