Metadata-Version: 2.1
Name: thumbor-plugins-gifv
Version: 0.1.5
Summary: Thumbor optimizer to add support to Gifv(mp4)
Home-page: https://github.com/thumbor/thumbor-plugins
Author: Guilherme Souza
Author-email: guilherme@souza.tech
License: MIT
Keywords: thumbor ffmpeg gifv mp4
Classifier: Development Status :: 4 - Beta
Classifier: Intended Audience :: Developers
Classifier: License :: OSI Approved :: MIT License
Classifier: Natural Language :: English
Classifier: Operating System :: MacOS
Classifier: Operating System :: POSIX :: Linux
Classifier: Programming Language :: Python :: 3
Classifier: Programming Language :: Python :: 3.7
Classifier: Programming Language :: Python :: 3.8
Classifier: Programming Language :: Python :: 3 :: Only
Classifier: Topic :: Internet :: WWW/HTTP :: Dynamic Content
Classifier: Topic :: Multimedia :: Graphics :: Presentation
Requires-Dist: webcolors ==1.*,>=1.13.0
